asynckeybow.py
asynckeybow-0.0.2.dist-info/LICENSE
asynckeybow-0.0.2.dist-info/METADATA
asynckeybow-0.0.2.dist-info/WHEEL
asynckeybow-0.0.2.dist-info/top_level.txt
asynckeybow-0.0.2.dist-info/RECORD
