Metadata-Version: 2.1
Name: asynckeybow
Version: 0.0.2
Summary: asyncio module for controlling a pimoroni keybow
Home-page: https://github.com/gerrowadat/asynckeybow
Author: Dave O'Connor
Author-email: doc+git@gerrup.eu
License: UNKNOWN
Platform: UNKNOWN
Classifier: Programming Language :: Python :: 3
Classifier: License :: OSI Approved :: Apache Software License
Classifier: Operating System :: OS Independent
Requires-Python: >=3.4
License-File: LICENSE
